.bumpversion.cfg
.coveragerc
.travis.tmpl.yml
.travis.yml
AUTHORS
CHANGES.rst
LICENSE
MANIFEST.in
README.rst
configure
django-easyfilters.komodoproject
setup.cfg
setup.py
tox.ini
tox.tmpl.ini
docs/Makefile
docs/conf.py
docs/develop.rst
docs/filters.rst
docs/filterset.rst
docs/index.rst
docs/install.rst
docs/make.bat
docs/overview.rst
docs/requirements.txt
src/django_easyfilters/__init__.py
src/django_easyfilters/filters.py
src/django_easyfilters/filterset.py
src/django_easyfilters/models.py
src/django_easyfilters/queries.py
src/django_easyfilters/ranges.py
src/django_easyfilters/utils.py
src/django_easyfilters/templates/django_easyfilters/default.html
src/django_easyfilters_ap.egg-info/PKG-INFO
src/django_easyfilters_ap.egg-info/SOURCES.txt
src/django_easyfilters_ap.egg-info/dependency_links.txt
src/django_easyfilters_ap.egg-info/not-zip-safe
src/django_easyfilters_ap.egg-info/requires.txt
src/django_easyfilters_ap.egg-info/top_level.txt
tests/test_app/__init__.py
tests/test_app/admin.py
tests/test_app/models.py
tests/test_app/urls.py
tests/test_app/views.py
tests/test_app/fixtures/django_easyfilters_tests.json
tests/test_app/templates/authors.html
tests/test_app/templates/base.html
tests/test_app/templates/book_search.html
tests/test_app/templates/books.html
tests/test_app/templates/template_for_tests.html
tests/test_app/tests/__init__.py
tests/test_app/tests/test_filterset.py
tests/test_app/tests/test_ranges.py
tests/test_project/__init__.py
tests/test_project/settings.py